neurostats_API/__init__.py
neurostats_API/cli.py
neurostats_API/main.py
neurostats_API/async_mode/__init__.py
neurostats_API/async_mode/db/__init__.py
neurostats_API/async_mode/db/base.py
neurostats_API/async_mode/db/tej.py
neurostats_API/async_mode/db/twse.py
neurostats_API/async_mode/db/us.py
neurostats_API/async_mode/db_extractors/__init__.py
neurostats_API/async_mode/db_extractors/base.py
neurostats_API/async_mode/db_extractors/daily/__init__.py
neurostats_API/async_mode/db_extractors/daily/base.py
neurostats_API/async_mode/db_extractors/daily/tej_chip.py
neurostats_API/async_mode/db_extractors/daily/tej_tech.py
neurostats_API/async_mode/db_extractors/daily/twse_chip.py
neurostats_API/async_mode/db_extractors/daily/value.py
neurostats_API/async_mode/db_extractors/daily/yf.py
neurostats_API/async_mode/db_extractors/month_revenue/__init__.py
neurostats_API/async_mode/db_extractors/month_revenue/base.py
neurostats_API/async_mode/db_extractors/month_revenue/twse.py
neurostats_API/async_mode/db_extractors/seasonal/__init__.py
neurostats_API/async_mode/db_extractors/seasonal/balance_sheet.py
neurostats_API/async_mode/db_extractors/seasonal/base.py
neurostats_API/async_mode/db_extractors/seasonal/cashflow.py
neurostats_API/async_mode/db_extractors/seasonal/profit_lose.py
neurostats_API/async_mode/db_extractors/seasonal/tej.py
neurostats_API/async_mode/factory/__init__.py
neurostats_API/async_mode/factory/extractor_factory.py
neurostats_API/async_mode/factory/transformer_factory.py
neurostats_API/async_mode/fetchers/__init__.py
neurostats_API/async_mode/fetchers/balance_sheet.py
neurostats_API/async_mode/fetchers/base.py
neurostats_API/async_mode/fetchers/cash_flow.py
neurostats_API/async_mode/fetchers/finance_overview.py
neurostats_API/async_mode/fetchers/month_revenue.py
neurostats_API/async_mode/fetchers/profit_lose.py
neurostats_API/async_mode/fetchers/tech.py
neurostats_API/async_mode/fetchers/twse_institution.py
neurostats_API/async_mode/fetchers/twse_margin.py
neurostats_API-1.0.0.dist-info/METADATA
neurostats_API-1.0.0.dist-info/WHEEL
neurostats_API-1.0.0.dist-info/top_level.txt
neurostats_API-1.0.0.dist-info/RECORD
