Metadata-Version: 2.1
Name: neurostats_API
Version: 1.0.0
Summary: The service of NeuroStats website
Home-page: https://github.com/NeurowattStats/NeuroStats_API.git
Author: JasonWang@Neurowatt
Author-email: jason@neurowatt.ai
Requires-Python: >=3.6
Requires-Dist: numpy
Requires-Dist: pandas
Requires-Dist: pymongo
Requires-Dist: pytz
Requires-Dist: python-dotenv
Requires-Dist: yfinance
Requires-Dist: holidays==0.70
